jupyter_next/__init__.py
jupyter_next/_version.py
jupyter_next/handlers.py
jupyter_next/tests/__init__.py
jupyter_next/tests/test_handlers.py
jupyter_next-0.0.3.data/data/etc/jupyter/jupyter_notebook_config.d/jupyter_next.json
jupyter_next-0.0.3.data/data/etc/jupyter/jupyter_server_config.d/jupyter_next.json
jupyter_next-0.0.3.data/data/share/jupyter/labextensions/@datalayer/jupyter-next/build_log.json
jupyter_next-0.0.3.data/data/share/jupyter/labextensions/@datalayer/jupyter-next/package.json
jupyter_next-0.0.3.data/data/share/jupyter/labextensions/@datalayer/jupyter-next/schemas/@datalayer/jupyter-docker/package.json.orig
jupyter_next-0.0.3.data/data/share/jupyter/labextensions/@datalayer/jupyter-next/schemas/@datalayer/jupyter-docker/plugin.json
jupyter_next-0.0.3.data/data/share/jupyter/labextensions/@datalayer/jupyter-next/static/lib_index_js.1908785d2de913b03e34.js
jupyter_next-0.0.3.data/data/share/jupyter/labextensions/@datalayer/jupyter-next/static/lib_index_js.1908785d2de913b03e34.js.map
jupyter_next-0.0.3.data/data/share/jupyter/labextensions/@datalayer/jupyter-next/static/node_modules_object-assign_index_js.e43fe12e0928341e123f.js
jupyter_next-0.0.3.data/data/share/jupyter/labextensions/@datalayer/jupyter-next/static/node_modules_object-assign_index_js.e43fe12e0928341e123f.js.map
jupyter_next-0.0.3.data/data/share/jupyter/labextensions/@datalayer/jupyter-next/static/remoteEntry.fa265c9e246a6a8a11fb.js
jupyter_next-0.0.3.data/data/share/jupyter/labextensions/@datalayer/jupyter-next/static/remoteEntry.fa265c9e246a6a8a11fb.js.map
jupyter_next-0.0.3.data/data/share/jupyter/labextensions/@datalayer/jupyter-next/static/style.js
jupyter_next-0.0.3.data/data/share/jupyter/labextensions/@datalayer/jupyter-next/static/style_index_js.a237203fa08c2cd0d4af.js
jupyter_next-0.0.3.data/data/share/jupyter/labextensions/@datalayer/jupyter-next/static/style_index_js.a237203fa08c2cd0d4af.js.map
jupyter_next-0.0.3.dist-info/METADATA
jupyter_next-0.0.3.dist-info/WHEEL
jupyter_next-0.0.3.dist-info/licenses/LICENSE
jupyter_next-0.0.3.dist-info/RECORD
